aiohttp_tus/__init__.py
aiohttp_tus/annotations.py
aiohttp_tus/constants.py
aiohttp_tus/data.py
aiohttp_tus/py.typed
aiohttp_tus/tus.py
aiohttp_tus/utils.py
aiohttp_tus/validators.py
aiohttp_tus/views.py
aiohttp_tus-1.1.0.dist-info/LICENSE
aiohttp_tus-1.1.0.dist-info/WHEEL
aiohttp_tus-1.1.0.dist-info/METADATA
aiohttp_tus-1.1.0.dist-info/RECORD
