Metadata-Version: 2.1
Name: aiohttp-tus
Version: 1.1.0
Summary: tus.io protocol implementation for aiohttp.web applications
Home-page: https://github.com/okumy/aiohttp-tus
License: BSD-3-Clause
Keywords: aiohttp,tus,tus.io
Author: Igor Davydenko
Author-email: iam@igordavydenko.com
Requires-Python: >=3.10,<4.0
Classifier: Development Status :: 5 - Production/Stable
Classifier: Environment :: Web Environment
Classifier: Framework :: AsyncIO
Classifier: Intended Audience :: Developers
Classifier: License :: OSI Approved :: BSD License
Classifier: Operating System :: OS Independent
Classifier: Programming Language :: Python :: 3
Classifier: Programming Language :: Python :: 3.10
Classifier: Topic :: Internet :: WWW/HTTP
Classifier: Topic :: Utilities
Classifier: Typing :: Typed
Requires-Dist: aiohttp (>=3.8.1,<4.0.0)
Project-URL: Documentation, https://aiohttp-tus.readthedocs.io/
Project-URL: Repository, https://github.com/okumy/aiohttp-tus
